django_bootstrap5/__about__.py
django_bootstrap5/__init__.py
django_bootstrap5/components.py
django_bootstrap5/core.py
django_bootstrap5/css.py
django_bootstrap5/forms.py
django_bootstrap5/html.py
django_bootstrap5/jinja2.py
django_bootstrap5/renderers.py
django_bootstrap5/size.py
django_bootstrap5/text.py
django_bootstrap5/utils.py
django_bootstrap5/widgets.py
django_bootstrap5/templates/django_bootstrap5/bootstrap5.html
django_bootstrap5/templates/django_bootstrap5/field_errors.html
django_bootstrap5/templates/django_bootstrap5/field_help_text.html
django_bootstrap5/templates/django_bootstrap5/form_errors.html
django_bootstrap5/templates/django_bootstrap5/messages.html
django_bootstrap5/templates/django_bootstrap5/pagination.html
django_bootstrap5/templates/django_bootstrap5/widgets/clearable_file_input.html
django_bootstrap5/templates/django_bootstrap5/widgets/radio_select.html
django_bootstrap5/templates/django_bootstrap5/widgets/radio_select_button_group.html
django_bootstrap5/templatetags/__init__.py
django_bootstrap5/templatetags/django_bootstrap5.py
django_bootstrap5-24.3.dist-info/AUTHORS
django_bootstrap5-24.3.dist-info/LICENSE
django_bootstrap5-24.3.dist-info/METADATA
django_bootstrap5-24.3.dist-info/WHEEL
django_bootstrap5-24.3.dist-info/top_level.txt
django_bootstrap5-24.3.dist-info/RECORD
