Metadata-Version: 2.1
Name: django-bootstrap5
Version: 24.3
Summary: Bootstrap 5 for Django
Author-email: Dylan Verheul <dylan@dyve.net>
License: BSD 3-Clause License
Project-URL: Changelog, https://github.com/zostera/django-bootstrap5/blob/main/CHANGELOG.md
Project-URL: Documentation, https://django-bootstrap5.readthedocs.io/
Project-URL: Homepage, https://github.com/zostera/django-bootstrap5
Project-URL: Issues, https://github.com/zostera/django-bootstrap5/issues
Project-URL: Source, https://github.com/zostera/django-bootstrap5
Keywords: django,bootstrap,bootstrap5
Classifier: Development Status :: 5 - Production/Stable
Classifier: Environment :: Web Environment
Classifier: Framework :: Django
Classifier: Framework :: Django :: 4.2
Classifier: Framework :: Django :: 5.0
Classifier: Framework :: Django :: 5.1
Classifier: Intended Audience :: Developers
Classifier: License :: OSI Approved :: BSD License
Classifier: Operating System :: OS Independent
Classifier: Programming Language :: Python :: 3
Classifier: Programming Language :: Python :: 3.8
Classifier: Programming Language :: Python :: 3.9
Classifier: Programming Language :: Python :: 3.10
Classifier: Programming Language :: Python :: 3.11
Classifier: Programming Language :: Python :: 3.12
Classifier: Topic :: Software Development :: Libraries
Classifier: Topic :: Utilities
Requires-Python: >=3.8
License-File: LICENSE
License-File: AUTHORS
Requires-Dist: Django>=4.2
Provides-Extra: jinja
Requires-Dist: Jinja2<4,>=3.0; extra == "jinja"
